bestOf/__init__.py
bestOf/backend/__init__.py
bestOf/backend/blinkDetector.py
bestOf/backend/classDefinitions.py
bestOf/backend/createBlinkModel.py
bestOf/backend/createCroppedFaceDataset.py
bestOf/backend/createCroppedFaceModel.py
bestOf/backend/createEyeSet.py
bestOf/backend/createScoreMaps.py
bestOf/backend/create_dataset.py
bestOf/backend/cropDetector.py
bestOf/backend/evaluateCentering.py
bestOf/backend/evaluateLighting.py
bestOf/backend/evaluateResolution.py
bestOf/backend/evaluateSharpness.py
bestOf/backend/identifyPeople.py
bestOf/backend/sampleNonBlinkers.py
bestOf/backend/settings.json
bestOf/backend/similarity.py
bestOf/backend/sitePackagePathConstructor.py
bestOf/backend/saved_models/__init__.py
bestOf/backend/saved_models/blinkingFaces.pth
bestOf/backend/saved_models/cropped_faces.pth
bestOf/frontend/__init__.py
bestOf/frontend/analyzing_page.py
bestOf/frontend/app.py
bestOf/frontend/frontend.py
bestOf/frontend/main.py
bestOf/frontend/menu.py
bestOf/frontend/res.py
bestOf/frontend/results.py
bestOf/frontend/settings.py
bestOf-0.0.90.dist-info/LICENSE
bestOf-0.0.90.dist-info/METADATA
bestOf-0.0.90.dist-info/WHEEL
bestOf-0.0.90.dist-info/entry_points.txt
bestOf-0.0.90.dist-info/top_level.txt
bestOf-0.0.90.dist-info/RECORD
