Metadata-Version: 2.1
Name: bestOf
Version: 0.0.90
Summary: A module that uses machine learning to chose the best image in groups
Home-page: https://github.com/apangasa/bestof
Author: UNKNOWN
Author-email: UNKNOWN
License: UNKNOWN
Platform: UNKNOWN
Requires-Dist: torch
Requires-Dist: torchvision
Requires-Dist: mediapipe
Requires-Dist: PyQt5
Requires-Dist: Pillow
Requires-Dist: matplotlib
Requires-Dist: opencv-python-headless
